hachoir/__init__.py
hachoir/grep.py
hachoir/strip.py
hachoir/test.py
hachoir/urwid.py
hachoir/core/__init__.py
hachoir/core/benchmark.py
hachoir/core/bits.py
hachoir/core/cmd_line.py
hachoir/core/config.py
hachoir/core/dict.py
hachoir/core/endian.py
hachoir/core/error.py
hachoir/core/event_handler.py
hachoir/core/i18n.py
hachoir/core/iso639.py
hachoir/core/language.py
hachoir/core/log.py
hachoir/core/memory.py
hachoir/core/profiler.py
hachoir/core/text_handler.py
hachoir/core/timeout.py
hachoir/core/tools.py
hachoir/editor/__init__.py
hachoir/editor/field.py
hachoir/editor/fieldset.py
hachoir/editor/typed_field.py
hachoir/field/__init__.py
hachoir/field/basic_field_set.py
hachoir/field/bit_field.py
hachoir/field/byte_field.py
hachoir/field/character.py
hachoir/field/enum.py
hachoir/field/fake_array.py
hachoir/field/field.py
hachoir/field/field_set.py
hachoir/field/float.py
hachoir/field/fragment.py
hachoir/field/generic_field_set.py
hachoir/field/helper.py
hachoir/field/integer.py
hachoir/field/link.py
hachoir/field/padding.py
hachoir/field/parser.py
hachoir/field/seekable_field_set.py
hachoir/field/static_field_set.py
hachoir/field/string_field.py
hachoir/field/sub_file.py
hachoir/field/timestamp.py
hachoir/field/vector.py
hachoir/metadata/__init__.py
hachoir/metadata/__main__.py
hachoir/metadata/archive.py
hachoir/metadata/audio.py
hachoir/metadata/config.py
hachoir/metadata/cr2.py
hachoir/metadata/csv.py
hachoir/metadata/file_system.py
hachoir/metadata/filter.py
hachoir/metadata/formatter.py
hachoir/metadata/gtk.py
hachoir/metadata/image.py
hachoir/metadata/jpeg.py
hachoir/metadata/main.py
hachoir/metadata/metadata.py
hachoir/metadata/metadata_item.py
hachoir/metadata/misc.py
hachoir/metadata/program.py
hachoir/metadata/register.py
hachoir/metadata/riff.py
hachoir/metadata/safe.py
hachoir/metadata/setter.py
hachoir/metadata/timezone.py
hachoir/metadata/video.py
hachoir/metadata/qt/__init__.py
hachoir/metadata/qt/main.py
hachoir/parser/__init__.py
hachoir-3.3.0.dist-info/COPYING
hachoir-3.3.0.dist-info/METADATA
hachoir-3.3.0.dist-info/WHEEL
hachoir-3.3.0.dist-info/entry_points.txt
hachoir-3.3.0.dist-info/top_level.txt
hachoir-3.3.0.dist-info/zip-safe
hachoir-3.3.0.dist-info/RECORD
