Metadata-Version: 2.1
Name: hachoir
Version: 3.3.0
Summary: Package of Hachoir parsers used to open binary files
Home-page: http://hachoir.readthedocs.io/
Author: Hachoir team (see AUTHORS file)
License: GNU GPL v2
Project-URL: Source, https://github.com/vstinner/hachoir
Classifier: Development Status :: 5 - Production/Stable
Classifier: Environment :: Console :: Curses
Classifier: Environment :: Plugins
Classifier: Intended Audience :: Developers
Classifier: Intended Audience :: Education
Classifier: License :: OSI Approved :: GNU General Public License (GPL)
Classifier: Natural Language :: English
Classifier: Operating System :: OS Independent
Classifier: Programming Language :: Python :: 3
Classifier: Topic :: Multimedia
Classifier: Topic :: Scientific/Engineering :: Information Analysis
Classifier: Topic :: Software Development :: Disassemblers
Classifier: Topic :: Software Development :: Interpreters
Classifier: Topic :: Software Development :: Libraries :: Python Modules
Classifier: Topic :: System :: Filesystems
Classifier: Topic :: Text Processing
Classifier: Topic :: Utilities
Provides-Extra: urwid
Provides-Extra: wx
License-File: COPYING
